ipfshttpclient/__init__.py
ipfshttpclient/encoding.py
ipfshttpclient/exceptions.py
ipfshttpclient/filescanner.py
ipfshttpclient/filescanner_ty.pyi
ipfshttpclient/http.py
ipfshttpclient/http_common.py
ipfshttpclient/http_httpx.py
ipfshttpclient/http_requests.py
ipfshttpclient/multipart.py
ipfshttpclient/requests_wrapper.py
ipfshttpclient/utils.py
ipfshttpclient/version.py
ipfshttpclient/client/__init__.py
ipfshttpclient/client/base.py
ipfshttpclient/client/bitswap.py
ipfshttpclient/client/block.py
ipfshttpclient/client/bootstrap.py
ipfshttpclient/client/config.py
ipfshttpclient/client/dag.py
ipfshttpclient/client/dht.py
ipfshttpclient/client/files.py
ipfshttpclient/client/key.py
ipfshttpclient/client/miscellaneous.py
ipfshttpclient/client/name.py
ipfshttpclient/client/object.py
ipfshttpclient/client/pin.py
ipfshttpclient/client/pubsub.py
ipfshttpclient/client/repo.py
ipfshttpclient/client/swarm.py
ipfshttpclient/client/unstable.py
ipfshttpclient-0.7.0.dist-info/LICENSE
ipfshttpclient-0.7.0.dist-info/WHEEL
ipfshttpclient-0.7.0.dist-info/METADATA
ipfshttpclient-0.7.0.dist-info/RECORD
