Metadata-Version: 1.1
Name: ipfshttpclient
Version: 0.7.0
Summary: Python IPFS HTTP CLIENT library
Home-page: https://ipfs.io/ipns/12D3KooWEqnTdgqHnkkwarSrJjeMP2ZJiADWLYADaNvUb6SQNyPF/
Author: py-ipfs-http-client team
Author-email: 
